{
  "main": {
    "id": "86d8677deb8052f7",
    "type": "split",
    "children": [
      {
        "id": "4a976d3a8bbea8ad",
        "type": "tabs",
        "children": [
          {
            "id": "d98173a922739b6d",
            "type": "leaf",
            "state": {
              "type": "markdown",
              "state": {
                "file": "docs/dm/loot/thargrin_letter.md",
                "mode": "source",
                "source": false
              },
              "icon": "lucide-file",
              "title": "thargrin_letter"
            }
          }
        ]
      }
    ],
    "direction": "vertical"
  },
  "left": {
    "id": "58c10cad190e3fea",
    "type": "split",
    "children": [
      {
        "id": "d6d35aa1e2afdcf2",
        "type": "tabs",
        "children": [
          {
            "id": "8b60e7fd6b137849",
            "type": "leaf",
            "state": {
              "type": "file-explorer",
              "state": {
                "sortOrder": "alphabetical",
                "autoReveal": false
              },
              "icon": "lucide-folder-closed",
              "title": "Files"
            }
          },
          {
            "id": "b3dc3abe08502b0b",
            "type": "leaf",
            "state": {
              "type": "search",
              "state": {
                "query": "",
                "matchingCase": false,
                "explainSearch": false,
                "collapseAll": false,
                "extraContext": false,
                "sortOrder": "alphabetical"
              },
              "icon": "lucide-search",
              "title": "Search"
            }
          },
          {
            "id": "5b63ec2e3f8098ee",
            "type": "leaf",
            "state": {
              "type": "bookmarks",
              "state": {},
              "icon": "lucide-bookmark",
              "title": "Bookmarks"
            }
          }
        ]
      }
    ],
    "direction": "horizontal",
    "width": 474.5
  },
  "right": {
    "id": "91e5495a9d011ac2",
    "type": "split",
    "children": [
      {
        "id": "09b82fe8925e3aac",
        "type": "tabs",
        "children": [
          {
            "id": "5bb71d72b10c3a09",
            "type": "leaf",
            "state": {
              "type": "backlink",
              "state": {
                "collapseAll": false,
                "extraContext": false,
                "sortOrder": "alphabetical",
                "showSearch": false,
                "searchQuery": "",
                "backlinkCollapsed": false,
                "unlinkedCollapsed": true
              },
              "icon": "links-coming-in",
              "title": "Backlinks"
            }
          },
          {
            "id": "089cfcc728eb2d49",
            "type": "leaf",
            "state": {
              "type": "outgoing-link",
              "state": {
                "linksCollapsed": false,
                "unlinkedCollapsed": true
              },
              "icon": "links-going-out",
              "title": "Outgoing links"
            }
          },
          {
            "id": "d6dffae1d820b230",
            "type": "leaf",
            "state": {
              "type": "tag",
              "state": {
                "sortOrder": "frequency",
                "useHierarchy": true,
                "showSearch": false,
                "searchQuery": ""
              },
              "icon": "lucide-tags",
              "title": "Tags"
            }
          },
          {
            "id": "d275840c41bbfb81",
            "type": "leaf",
            "state": {
              "type": "outline",
              "state": {
                "followCursor": false,
                "showSearch": false,
                "searchQuery": ""
              },
              "icon": "lucide-list",
              "title": "Outline"
            }
          }
        ]
      }
    ],
    "direction": "horizontal",
    "width": 300,
    "collapsed": true
  },
  "left-ribbon": {
    "hiddenItems": {
      "switcher:Open quick switcher": false,
      "graph:Open graph view": false,
      "canvas:Create new canvas": false,
      "daily-notes:Open today's daily note": false,
      "templates:Insert template": false,
      "command-palette:Open command palette": false
    }
  },
  "active": "d98173a922739b6d",
  "lastOpenFiles": [
    "docs/dm/loot/topaz.md",
    "docs/dm/loot/thargrin_letter.md",
    "docs/dm/loot/staff_of_flowers.md",
    "docs/dm/loot/sala_subterranea_frascos.md",
    "docs/dm/loot/reliquia_amaldicoada.md",
    "docs/dm/loot/pocao_resistencia_necrotico.md",
    "docs/dm/loot/pocao_da_esperanca.md",
    "docs/dm/loot/pergaminho_expulsar_mortos_vivos.md",
    "docs/dm/loot/medalhao_do_sussurro.md",
    "docs/dm/loot/manto_sombra_viva.md",
    "docs/dm/loot/loot_vento_sombrio.md",
    "docs/dm/loot/loot_sessao1.md",
    "docs/dm/loot/loot.md",
    "docs/dm/loot/livro_druida.md",
    "docs/dm/loot/hook_horror_teeth.md",
    "docs/dm/loot/gema_das_cinco_vozes.md",
    "docs/dm/loot/espada_luz_velada.md",
    "docs/dm/loot/capa_da_neblina.md",
    "docs/dm/loot/bracers_of_defense.md",
    "docs/dm/loot/blank.png",
    "docs/dm/loot/artefatos_e_itens.md",
    "docs/dm/loot/anel_magico_de_zorg.md",
    "docs/dm/loot/acorn_borogrove.md",
    "docs/locations/ulek/ulek.md",
    "docs/locations/veluna/veluna.md",
    "docs/locations/veluna/blank.png",
    "docs/dm/pc/pc_zeldris_varus.md",
    "lter .bak  Remove-Item -Force",
    "New Documento de Texto.txt",
    "docs/index.md",
    "scripts/gen_nav.py",
    "scripts/New Documento de Texto.txt",
    "tools/folder_structure_gui.py",
    "tools/folders_structure.py.txt",
    "tools/New Documento de Texto.txt",
    "tools/gen_nav.py",
    "tools/fix_mojibake.py",
    "docs/dm/pc/pc_frederick_freddy_01.png",
    "docs/dm/pc/pc_arkos_vasell.png",
    "docs/dm/ - Copy.pages",
    "docs/pc/pc_raylahn.jpg",
    "docs/monsters/swarm_of_rats.jpeg",
    "docs/monsters/swarm_of_bats.png",
    "docs/adventures/missing_person.png",
    "docs/adventures/mapDM.png",
    "docs/adventures/mapa_caminho.png"
  ]
}